TPTBox/__init__.py
TPTBox/core/__init__.py
TPTBox/core/bids_constants.py
TPTBox/core/bids_files.py
TPTBox/core/compat.py
TPTBox/core/dicom/__init__.py
TPTBox/core/dicom/dicom2nii_utils.py
TPTBox/core/dicom/dicom_extract.py
TPTBox/core/dicom/dicom_header_to_keys.py
TPTBox/core/dicom/fix_brocken.py
TPTBox/core/dicom/nii2dicom.py
TPTBox/core/internal/__init__.py
TPTBox/core/internal/ants_load.py
TPTBox/core/internal/deep_learning_utils.py
TPTBox/core/internal/nii_help.py
TPTBox/core/internal/slicer_nrrd.py
TPTBox/core/nii_poi_abstract.py
TPTBox/core/nii_wrapper.py
TPTBox/core/nii_wrapper_math.py
TPTBox/core/np_utils.py
TPTBox/core/poi.py
TPTBox/core/poi_fun/__init__.py
TPTBox/core/poi_fun/_help.py
TPTBox/core/poi_fun/pixel_based_point_finder.py
TPTBox/core/poi_fun/poi_abstract.py
TPTBox/core/poi_fun/poi_global.py
TPTBox/core/poi_fun/ray_casting.py
TPTBox/core/poi_fun/save_load.py
TPTBox/core/poi_fun/save_mkr.py
TPTBox/core/poi_fun/strategies.py
TPTBox/core/poi_fun/vertebra_direction.py
TPTBox/core/poi_fun/vertebra_pois_non_centroids.py
TPTBox/core/sitk_utils.py
TPTBox/core/vert_constants.py
TPTBox/images/logo.svg
TPTBox/images/poi_preview.png
TPTBox/images/snp2D_example.png
TPTBox/images/snp3D_example.jpg
TPTBox/logger/__init__.py
TPTBox/logger/log_constants.py
TPTBox/logger/log_file.py
TPTBox/mesh3D/__init__.py
TPTBox/mesh3D/html_preview.py
TPTBox/mesh3D/mesh.py
TPTBox/mesh3D/mesh_colors.py
TPTBox/mesh3D/snapshot3D.py
TPTBox/registration/__init__.py
TPTBox/registration/deepali/__init__.py
TPTBox/registration/deepali/_hooks.py
TPTBox/registration/deepali/_utils.py
TPTBox/registration/deepali/deepali_model.py
TPTBox/registration/deepali/deepali_trainer.py
TPTBox/registration/deepali/spine_rigid_elements_reg.py
TPTBox/registration/deformable/__init__.py
TPTBox/registration/deformable/_deepali/__init__.py
TPTBox/registration/deformable/_deepali/deform_reg_pair.py
TPTBox/registration/deformable/_deepali/deformable_config.yaml
tptbox-0.5.2.dist-info/METADATA
tptbox-0.5.2.dist-info/WHEEL
tptbox-0.5.2.dist-info/licenses/LICENSE
tptbox-0.5.2.dist-info/RECORD
