Metadata-Version: 2.4
Name: TPTBox
Version: 0.5.2
Summary: A Torso Processing Toolbox capable of processing BIDS-compatible datasets, singular niftys, points of interests, segmentations, and much more.
License: GNU AFFERO GENERAL PUBLIC LICENSE v3.0, 19 November 2007
License-File: LICENSE
Author: Robert Graf
Author-email: robert.graf@tum.de
Requires-Python: >=3.9,<4.0
Classifier: License :: Other/Proprietary License
Classifier: Programming Language :: Python :: 3
Classifier: Programming Language :: Python :: 3.9
Classifier: Programming Language :: Python :: 3.10
Classifier: Programming Language :: Python :: 3.11
Classifier: Programming Language :: Python :: 3.12
Classifier: Programming Language :: Python :: 3.13
Classifier: Programming Language :: Python :: 3.14
Requires-Dist: SimpleITK (>=2.3.1,<3.0.0)
Requires-Dist: antspyx (==0.4.2)
Requires-Dist: connected-components-3d (>=3.12.3,<4.0.0)
Requires-Dist: dataclasses
Requires-Dist: dill (>=0.3.7,<0.4.0)
Requires-Dist: fill-voids (>=2.0.6,<3.0.0)
Requires-Dist: joblib
Requires-Dist: matplotlib (>=3.8.2,<4.0.0)
Requires-Dist: nibabel (>=5.2.0,<6.0.0)
Requires-Dist: numpy (>=1.26.3,<2.0.0)
Requires-Dist: pathlib
Requires-Dist: pynrrd
Requires-Dist: scikit-image (>=0.22.0,<0.23.0)
Requires-Dist: scikit-learn
Requires-Dist: scipy (>=1.12.0,<2.0.0)
Requires-Dist: tqdm
Requires-Dist: typing-extensions (>=4.9.0,<5.0.0)
Project-URL: Repository, https://github.com/Hendrik-code/TPTBox
